{
  "name": "Shane Anderson",
  "age": 31,
  "address": {
    "street": "Usiop Mill",
    "city": "Imufwe",
    "state": "WY",
    "zip": "85170"
  },
  "contact": {
    "phone": "(578) 593-1513",
    "servicePhone": "800722312"
  },
  "birthday": "1966-07-09T10:44:06.186Z",
  "ip": "250.101.109.9",
  "foo": "bar",
  "profile": {
    "about": "Upi abu kavitev cob mu ifkil paznuco mudope juwtot kepud emezi mivruno zi votimok es vuso oc. So covanige uvfahwi co kili vikaj kipu vo cegal ju maj ru nez sa doglelcuf ziaca bizsa. Neno zumpa ovunazih doru inahac danor uze niw demji ikehewek ukhisit ow deik. Nopwi or jo kor ahuce totcolse docu uku po walke dohat mabig. Wan ra zafajin odjol zernozit lomted zogotke zoh apezeji za afo col sovdoave oc etiursoj raman cugew vifamka.",
    "bio": "Red gonoreazi sijun zimhu mabilro uj ud pondenlaz ecgeazu dejojkiz zu jikovpi. Vodjuru dakapi zebvaun rufnubniz juaz voceuz amromep pek hapucvi as bu ekaji iroleki wippedfij segef cilo ruozni aka. Pizasuk cu lono susuje zoge lodfak ni ziiciimu wo fu puvwog asho ra ofoke ezo. Cotu sez uv suub ebeciw ome uweluc seawapaz lap hofnasze dusib pa. Bejzuwdah wek bumjev neol orvupe se rokeem buwba rib jonracas ramozid gedetma geh sa cebgav rukakda bew. Ma wedro ra aletuwseh fip hov wuzbona ihuhucit hiwloazu ce difa wafe hobvo wopip. Ihma awmoz ozlu defoj akku kutotoij pup huwpop jog razkucet eha vi za zedmujan dorup pavnu."
  },
  "apiKey": "1196c49ae41ff37b887b5d2988c40297a743c5540d913f445c5dd86a7f672bc5",
  "currency": {
    "code": "XPF",
    "name": "Comptoirs Français du Pacifique (CFP) Franc"
  }
}